{
  "id": "hubei",
  "name": "湖北省",
  "cities": [
    {
      "id": "wuhan",
      "name": "武汉市",
      "population": 13774000,
      "gdp": 20011.0,
      "perCapitaDisposableIncome": 53000,
      "averageHousePrice": 22000,
      "licensePlate": "鄂A",
      "idPrefix": "420100",
      "location": [114.298572, 30.584355],
      "attractions": ["黄鹤楼", "东湖", "武汉大学", "汉口江滩", "归元寺"],
      "cuisine": ["热干面", "豆皮", "武昌鱼", "排骨藕汤", "面窝"],
      "universities": ["武汉大学", "华中科技大学", "华中师范大学", "中南财经政法大学"],
      "businessDistricts": ["江岸区", "江汉区", "硚口区", "汉阳区", "武昌区"],
      "famousPeople": ["毛泽东", "周恩来", "邓小平", "陈独秀", "李大钊"]
    },
    {
      "id": "huangshi",
      "name": "黄石市",
      "population": 2410000,
      "gdp": 1800.0,
      "perCapitaDisposableIncome": 38000,
      "averageHousePrice": 12000,
      "licensePlate": "鄂B",
      "idPrefix": "420200",
      "location": [115.077048, 30.220074],
      "attractions": ["黄石国家矿山公园", "磁湖", "西塞山", "东方山", "雷山风景区"],
      "cuisine": ["黄石港饼", "土豆片", "炸辣椒", "港饼", "肉糕"],
      "universities": ["湖北师范大学", "湖北理工学院"],
      "businessDistricts": ["黄石港区", "西塞山区", "下陆区", "铁山区"],
      "famousPeople": ["林育英", "林育南", "项英", "林彪", "王任重"]
    },
    {
      "id": "shiyan",
      "name": "十堰市",
      "population": 3100000,
      "gdp": 2200.0,
      "perCapitaDisposableIncome": 37000,
      "averageHousePrice": 13000,
      "licensePlate": "鄂C",
      "idPrefix": "420300",
      "location": [110.787916, 32.646907],
      "attractions": ["武当山", "丹江口水库", "神农架", "郧阳博物馆", "四方山"],
      "cuisine": ["三合汤", "郧阳酸浆面", "竹溪腊肉", "房县小花菇", "竹山肚丝"],
      "universities": ["湖北汽车工业学院", "汉江师范学院"],
      "businessDistricts": ["茅箭区", "张湾区", "郧阳区", "丹江口市"],
      "famousPeople": ["张三丰", "李时珍", "陈世美", "王世贞", "张居正"]
    },
    {
      "id": "jingzhou",
      "name": "荆州市",
      "population": 5100000,
      "gdp": 2800.0,
      "perCapitaDisposableIncome": 35000,
      "averageHousePrice": 11000,
      "licensePlate": "鄂D",
      "idPrefix": "421000",
      "location": [112.23813, 30.326857],
      "attractions": ["荆州古城", "楚王车马阵", "关公义园", "洈水风景区", "张居正故居"],
      "cuisine": ["荆州鱼糕", "千张扣肉", "荆州豆瓣酱", "公安牛肉", "松滋鸡"],
      "universities": ["长江大学"],
      "businessDistricts": ["沙市区", "荆州区", "江陵县", "石首市"],
      "famousPeople": ["关羽", "张飞", "刘备", "诸葛亮", "张居正"]
    },
    {
      "id": "yichang",
      "name": "宜昌市",
      "population": 3800000,
      "gdp": 5500.0,
      "perCapitaDisposableIncome": 42000,
      "averageHousePrice": 15000,
      "licensePlate": "鄂E",
      "idPrefix": "420500",
      "location": [111.290843, 30.702636],
      "attractions": ["三峡大坝", "三峡人家", "清江画廊", "屈原故里", "三峡森林公园"],
      "cuisine": ["宜昌凉虾", "萝卜饺子", "秭归脐橙", "宜昌红茶", "顶顶糕"],
      "universities": ["三峡大学"],
      "businessDistricts": ["西陵区", "伍家岗区", "点军区", "猇亭区"],
      "famousPeople": ["屈原", "王昭君", "嫘祖", "杨守敬", "欧阳修"]
    },
    {
      "id": "xiangyang",
      "name": "襄阳市",
      "population": 5500000,
      "gdp": 5200.0,
      "perCapitaDisposableIncome": 41000,
      "averageHousePrice": 14000,
      "licensePlate": "鄂F",
      "idPrefix": "420600",
      "location": [112.144146, 32.042426],
      "attractions": ["古隆中", "襄阳古城", "唐城", "米公祠", "水镜庄"],
      "cuisine": ["襄阳牛肉面", "宜城大虾", "金刚酥", "孔明菜", "三镶盘"],
      "universities": ["湖北文理学院"],
      "businessDistricts": ["襄城区", "樊城区", "襄州区", "枣阳市"],
      "famousPeople": ["诸葛亮", "孟浩然", "米芾", "宋玉", "刘秀"]
    },
    {
      "id": "ezhou",
      "name": "鄂州市",
      "population": 1070000,
      "gdp": 1300.0,
      "perCapitaDisposableIncome": 40000,
      "averageHousePrice": 13000,
      "licensePlate": "鄂G",
      "idPrefix": "420700",
      "location": [114.890593, 30.396536],
      "attractions": ["西山", "莲花山", "鄂州长江大桥", "梁子湖", "吴王城"],
      "cuisine": ["武昌鱼", "鄂州豆丝", "太和千张", "胡柚", "鲊广椒"],
      "universities": ["鄂州职业大学"],
      "businessDistricts": ["梁子湖区", "华容区", "鄂城区"],
      "famousPeople": ["元结", "苏轼", "苏辙", "王禹偁", "毕昇"]
    },
    {
      "id": "jingmen",
      "name": "荆门市",
      "population": 2500000,
      "gdp": 2100.0,
      "perCapitaDisposableIncome": 36000,
      "averageHousePrice": 12000,
      "licensePlate": "鄂H",
      "idPrefix": "420800",
      "location": [112.199427, 31.03542],
      "attractions": ["明显陵", "漳河风景区", "彭墩乡村世界", "绿林山", "太子山"],
      "cuisine": ["荆门矮子馅饼", "钟祥盘龙菜", "京山桥米", "沙洋拾回桥手工挂面", "蟠龙菜"],
      "universities": ["荆楚理工学院"],
      "businessDistricts": ["东宝区", "掇刀区", "沙洋县", "钟祥市"],
      "famousPeople": ["宋玉", "刘勰", "郭店楚简", "屈原", "莫愁女"]
    },
    {
      "id": "xiaogan",
      "name": "孝感市",
      "population": 4200000,
      "gdp": 2700.0,
      "perCapitaDisposableIncome": 34000,
      "averageHousePrice": 11000,
      "licensePlate": "鄂K",
      "idPrefix": "420900",
      "location": [113.926655, 30.926423],
      "attractions": ["双峰山", "董永公园", "云梦博物馆", "观音湖", "白兆山"],
      "cuisine": ["孝感米酒", "麻糖", "汈汊湖莲子", "云梦鱼面", "安陆南乡萝卜"],
      "universities": ["湖北工程学院"],
      "businessDistricts": ["孝南区", "孝昌县", "大悟县", "云梦县"],
      "famousPeople": ["董永", "黄香", "孟宗", "李白", "陶侃"]
    },
    {
      "id": "huanggang",
      "name": "黄冈市",
      "population": 5700000,
      "gdp": 3100.0,
      "perCapitaDisposableIncome": 33000,
      "averageHousePrice": 10000,
      "licensePlate": "鄂J",
      "idPrefix": "421100",
      "location": [114.879365, 30.447711],
      "attractions": ["东坡赤壁", "遗爱湖", "大别山", "天堂寨", "红安县"],
      "cuisine": ["东坡肉", "黄州豆腐", "蕲春艾草", "武穴酥糖", "麻城菊花"],
      "universities": ["黄冈师范学院"],
      "businessDistricts": ["黄州区", "团风县", "红安县", "罗田县"],
      "famousPeople": ["苏轼", "李时珍", "毕昇", "陈潭秋", "林彪"]
    },
    {
      "id": "xianning",
      "name": "咸宁市",
      "population": 2500000,
      "gdp": 1700.0,
      "perCapitaDisposableIncome": 35000,
      "averageHousePrice": 11000,
      "licensePlate": "鄂L",
      "idPrefix": "421200",
      "location": [114.328963, 29.832798],
      "attractions": ["九宫山", "陆水湖", "隐水洞", "赤壁古战场", "温泉"],
      "cuisine": ["咸宁桂花糕", "簰洲圆子", "通山包陀", "崇阳红薯粉", "赤壁鱼糕"],
      "universities": ["湖北科技学院"],
      "businessDistricts": ["咸安区", "嘉鱼县", "通城县", "崇阳县"],
      "famousPeople": ["叶挺", "王世杰", "成仿吾", "钱亦石", "何功伟"]
    },
    {
      "id": "xiantao",
      "name": "仙桃市",
      "population": 1100000,
      "gdp": 1000.0,
      "perCapitaDisposableIncome": 34000,
      "averageHousePrice": 10000,
      "licensePlate": "鄂M",
      "idPrefix": "429004",
      "location": [113.453974, 30.364953],
      "attractions": ["沔城风景区", "梦里水乡", "排湖", "沙湖国家湿地公园", "狄仁杰文化公园"],
      "cuisine": ["沔阳三蒸", "仙桃米酒", "剅河豆丝", "张沟黄鳝", "沔城藕"],
      "universities": ["江汉大学文理学院"],
      "businessDistricts": ["沙嘴街道", "干河街道", "龙华山办事处", "郑场镇"],
      "famousPeople": ["陈友谅", "王平", "王莉", "雷军", "李小双"]
    },
    {
      "id": "qianjiang",
      "name": "潜江市",
      "population": 1000000,
      "gdp": 1200.0,
      "perCapitaDisposableIncome": 36000,
      "averageHousePrice": 11000,
      "licensePlate": "鄂N",
      "idPrefix": "429005",
      "location": [112.896866, 30.421215],
      "attractions": ["曹禺公园", "返湾湖国家湿地公园", "龙湾遗址", "章华台", "熊口小镇"],
      "cuisine": ["潜江小龙虾", "财鱼面", "焌米茶", "油焖大虾", "汽水包"],
      "universities": ["江汉艺术职业学院"],
      "businessDistricts": ["园林办事处", "广华办事处", "杨市办事处", "周矶办事处"],
      "famousPeople": ["曹禺", "李汉魂", "聂绀弩", "张难先", "陈先霖"]
    },
    {
      "id": "shennongjia",
      "name": "神农架林区",
      "population": 77000,
      "gdp": 35.0,
      "perCapitaDisposableIncome": 38000,
      "averageHousePrice": 12000,
      "licensePlate": "鄂P",
      "idPrefix": "429021",
      "location": [110.671525, 31.744449],
      "attractions": ["神农顶", "神农坛", "天燕", "大九湖", "官门山"],
      "cuisine": ["神农架野菜", "腊肉", "炕土豆", "懒豆腐", "苞谷酒"],
      "universities": [],
      "businessDistricts": ["松柏镇", "阳日镇", "木鱼镇", "红坪镇"],
      "famousPeople": ["炎帝神农", "野人传说", "护林员", "科考队员", "生态研究者"]
    },
    {
      "id": "enshi",
      "name": "恩施土家族苗族自治州",
      "population": 3300000,
      "gdp": 1400.0,
      "perCapitaDisposableIncome": 31000,
      "averageHousePrice": 9000,
      "licensePlate": "鄂Q",
      "idPrefix": "422800",
      "location": [109.48699, 30.283114],
      "attractions": ["恩施大峡谷", "腾龙洞", "梭布垭石林", "土司城", "屏山峡谷"],
      "cuisine": ["恩施玉露茶", "土家腊肉", "合渣", "炕土豆", "油茶汤"],
      "universities": ["湖北民族大学"],
      "businessDistricts": ["恩施市", "利川市", "建始县", "巴东县"],
      "famousPeople": ["容美土司", "田氏家族", "覃氏家族", "土家族英雄", "苗族文化传承人"]
    },
    {
      "id": "tianmen",
      "name": "天门市",
      "population": 1100000,
      "gdp": 800.0,
      "perCapitaDisposableIncome": 33000,
      "averageHousePrice": 9500,
      "licensePlate": "鄂R",
      "idPrefix": "429006",
      "location": [113.165862, 30.653061],
      "attractions": ["茶圣故里园", "陆羽纪念馆", "胡家花园", "石家河遗址", "天门山"],
      "cuisine": ["天门蒸菜", "岳口豆丝", "张港花椰菜", "九蒸九晒芝麻丸", "锅盔"],
      "universities": ["湖北天门职业学院"],
      "businessDistricts": ["竟陵街道", "侨乡街道", "杨林街道", "岳口镇"],
      "famousPeople": ["陆羽", "钟惺", "谭元春", "鲁铎", "陈良训"]
    },
    {
      "id": "suizhou",
      "name": "随州市",
      "population": 2000000,
      "gdp": 1100.0,
      "perCapitaDisposableIncome": 32000,
      "averageHousePrice": 10000,
      "licensePlate": "鄂S",
      "idPrefix": "421300",
      "location": [113.37377, 31.717497],
      "attractions": ["炎帝神农故里", "大洪山", "曾侯乙墓", "千年银杏谷", "漂水温泉"],
      "cuisine": ["随州泡泡油糕", "随州拐子饭", "广水滑滑鱼", "随州蜜枣", "随县板栗"],
      "universities": ["随州职业技术学院"],
      "businessDistricts": ["曾都区", "随县", "广水市"],
      "famousPeople": ["炎帝神农", "季梁", "杨坚", "李白", "米芾"]
    }
  ]
}